pylsd/__init__.py
pylsd/lsd.py
pylsd/lib.cpython-37m-x86_64-linux-gnu.so
pylsd/bindings/__init__.py
pylsd/bindings/lsd_ctypes.py
ocrd_fork_pylsd-0.0.8.dist-info/RECORD
ocrd_fork_pylsd-0.0.8.dist-info/LICENSE
ocrd_fork_pylsd-0.0.8.dist-info/WHEEL
ocrd_fork_pylsd-0.0.8.dist-info/METADATA
ocrd_fork_pylsd-0.0.8.dist-info/top_level.txt
