Metadata-Version: 2.1
Name: ocrd-fork-pylsd
Version: 0.0.8
Summary: pylsd is the python bindings for LSD - Line Segment Detector
Home-page: https://github.com/OCR-D/pylsd
Author: Gefu Tang
Author-email: tanggefu@gmail.com
Maintainer: kba
License: AGPL
Keywords: LSD,line segmentation
License-File: LICENSE
Requires-Dist: numpy
